torob_less_price_finder/__init__.py
torob_less_price_finder/cli.py
torob_prices-0.0.5.dist-info/licenses/LICENSE
torob_prices-0.0.5.dist-info/METADATA
torob_prices-0.0.5.dist-info/WHEEL
torob_prices-0.0.5.dist-info/entry_points.txt
torob_prices-0.0.5.dist-info/top_level.txt
torob_prices-0.0.5.dist-info/RECORD
