Metadata-Version: 2.4
Name: torob-prices
Version: 0.0.5
Summary: A simple web scraper to find the lowest price of a product on Torob.
Author-email: jajoul <jajoul.me@gmail.com>
Project-URL: Homepage, https://github.com/jajoul/torob-prices
Project-URL: Bug Tracker, https://github.com/jajoul/torob-prices/issues
Classifier: Programming Language :: Python :: 3
Classifier: License :: OSI Approved :: MIT License
Classifier: Operating System :: OS Independent
Requires-Python: >=3.7
License-File: LICENSE
Requires-Dist: requests
Requires-Dist: beautifulsoup4
Dynamic: license-file
